mastodon_finder/__about__.py
mastodon_finder/__init__.py
mastodon_finder/__main__.py
mastodon_finder/auth.py
mastodon_finder/discovery.py
mastodon_finder/enrich.py
mastodon_finder/finder.py
mastodon_finder/init.py
mastodon_finder/llm_runner.py
mastodon_finder/mastodon_client.py
mastodon_finder/prompt_builder.py
mastodon_finder/py.typed
mastodon_finder/report.py
mastodon_finder/settings.py
mastodon_finder/utils/__init__.py
mastodon_finder/utils/cli_suggestions.py
mastodon_finder/utils/logging_config.py
mastodon_finder-0.1.0.dist-info/METADATA
mastodon_finder-0.1.0.dist-info/WHEEL
mastodon_finder-0.1.0.dist-info/entry_points.txt
mastodon_finder-0.1.0.dist-info/licenses/LICENSE
mastodon_finder-0.1.0.dist-info/RECORD
