Metadata-Version: 2.4
Name: mastodon-finder
Version: 0.1.0
Summary: Search for mastodon profiles, use mechanical and LLM filtering.
Project-URL: Repository, https://github.com/matthewdeanmartin/mastodon_finder
Project-URL: Documentation, https://mastodon-finder.readthedocs.io/en/latest/
Project-URL: Changelog, https://github.com/matthewdeanmartin/mastodon_finder/blob/main/CHANGELOG.md
Project-URL: homepage, https://github.com/matthewdeanmartin/mastodon_finder
Project-URL: issues, https://github.com/matthewdeanmartin/mastodon_finder/issues/
Author-email: Matthew Dean Martin <matthewdeanmartin@gmail.com>
License-File: LICENSE
Keywords: mastodon
Classifier: Development Status :: 1 - Planning
Classifier: Environment :: Console
Classifier: Framework :: Pydantic
Classifier: License :: OSI Approved :: MIT License
Classifier: Operating System :: OS Independent
Classifier: Programming Language :: Python
Classifier: Programming Language :: Python :: 3.9
Classifier: Programming Language :: Python :: 3.10
Classifier: Programming Language :: Python :: 3.11
Classifier: Programming Language :: Python :: 3.12
Classifier: Programming Language :: Python :: 3.13
Classifier: Programming Language :: Python :: 3.14
Classifier: Topic :: Communications :: Chat
Classifier: Topic :: Internet
Classifier: Topic :: Internet :: WWW/HTTP
Classifier: Topic :: Utilities
Classifier: Typing :: Typed
Requires-Python: >=3.8
Requires-Dist: beautifulsoup4
Requires-Dist: colorlog
Requires-Dist: langdetect
Requires-Dist: mastodon-py
Requires-Dist: openai
Requires-Dist: pydantic-settings
Requires-Dist: python-dotenv
Requires-Dist: rich
Requires-Dist: tomli
